dimcat/__init__.py
dimcat/base.py
dimcat/cli.py
dimcat/dc_exceptions.py
dimcat/dc_warnings.py
dimcat/enums.py
dimcat/plotting.py
dimcat/settings.ini
dimcat/utils.py
dimcat/data/__init__.py
dimcat/data/base.py
dimcat/data/utils.py
dimcat/data/catalogs/__init__.py
dimcat/data/catalogs/base.py
dimcat/data/catalogs/inputs.py
dimcat/data/catalogs/outputs.py
dimcat/data/datasets/__init__.py
dimcat/data/datasets/base.py
dimcat/data/datasets/processed.py
dimcat/data/packages/__init__.py
dimcat/data/packages/base.py
dimcat/data/packages/dc.py
dimcat/data/packages/score.py
dimcat/data/resources/__init__.py
dimcat/data/resources/base.py
dimcat/data/resources/dc.py
dimcat/data/resources/facets.py
dimcat/data/resources/features.py
dimcat/data/resources/results.py
dimcat/data/resources/utils.py
dimcat/steps/__init__.py
dimcat/steps/base.py
dimcat/steps/analyzers/__init__.py
dimcat/steps/analyzers/base.py
dimcat/steps/analyzers/counters.py
dimcat/steps/analyzers/phrases.py
dimcat/steps/analyzers/prevalence.py
dimcat/steps/analyzers/proportions.py
dimcat/steps/extractors/__init__.py
dimcat/steps/extractors/base.py
dimcat/steps/filters/__init__.py
dimcat/steps/filters/annotations.py
dimcat/steps/filters/base.py
dimcat/steps/groupers/__init__.py
dimcat/steps/groupers/annotations.py
dimcat/steps/groupers/base.py
dimcat/steps/groupers/columns.py
dimcat/steps/groupers/metadata.py
dimcat/steps/loaders/__init__.py
dimcat/steps/loaders/base.py
dimcat/steps/loaders/m21.py
dimcat/steps/loaders/musescore.py
dimcat/steps/loaders/utils.py
dimcat/steps/pipelines/__init__.py
dimcat/steps/pipelines/base.py
dimcat/steps/slicers/__init__.py
dimcat/steps/slicers/base.py
dimcat/steps/slicers/feature_dimensions.py
dimcat-3.4.0.dist-info/METADATA
dimcat-3.4.0.dist-info/WHEEL
dimcat-3.4.0.dist-info/entry_points.txt
dimcat-3.4.0.dist-info/top_level.txt
dimcat-3.4.0.dist-info/RECORD
