Metadata-Version: 2.1
Name: dimcat
Version: 3.4.0
Summary: DIgital Musicology Corpus Analysis Toolkit
Home-page: https://github.com/DCMLab/dimcat
Author: Digital and Cognitive Musicology Lab @ École Polytechnique Fédérale de Lausanne
Author-email: johannes.hentschel@epfl.ch
License: GPL-3.0-or-later
Project-URL: Documentation, https://dcmlab.github.io/dimcat/
Platform: any
Classifier: Development Status :: 4 - Beta
Classifier: Programming Language :: Python
Requires-Python: >=3.10
Requires-Dist: colorlover~=0.3.0
Requires-Dist: frictionless[pandas,visidata,zenodo]>=5.17.1
Requires-Dist: kaleido~=0.2.1
Requires-Dist: marshmallow>=3.20.2
Requires-Dist: ms3>=2.4.4
Requires-Dist: music21>=9.1.0
Requires-Dist: pandas<2.2.0,>=2.0.0
Requires-Dist: plotly>=5.18.0
Requires-Dist: scipy~=1.12.0
Provides-Extra: dev
Requires-Dist: dimcat[testing]; extra == "dev"
Requires-Dist: dimcat[docs]; extra == "dev"
Requires-Dist: pre-commit; extra == "dev"
Provides-Extra: docs
Requires-Dist: jupyter-sphinx==0.4.0; extra == "docs"
Requires-Dist: linkify-it-py~=2.0.2; extra == "docs"
Requires-Dist: myst-nb~=0.17.2; extra == "docs"
Requires-Dist: pitchtypes>=0.4.0; extra == "docs"
Requires-Dist: sphinx~=5.3.0; extra == "docs"
Requires-Dist: pydata-sphinx-theme==0.13.3; extra == "docs"
Requires-Dist: jupytext; extra == "docs"
Provides-Extra: testing
Requires-Dist: pytest-cov~=4.1.0; extra == "testing"
Requires-Dist: pytest~=7.4.2; extra == "testing"
Requires-Dist: pyproject-api~=1.6.1; extra == "testing"
Requires-Dist: tox~=4.11.3; extra == "testing"
